trsp/__init__.py
trsp/build/__init__.py
trsp/build/_build_pbtxt.py
trsp/build/_file_config.py
trsp/run/__init__.py
trsp/utils/__init__.py
trsp/utils/_abstract.py
trsp/utils/_constants.py
trsp/utils/_docker.py
trsp/utils/_utils.py
trsp-0.0.4.dist-info/LICENCE
trsp-0.0.4.dist-info/METADATA
trsp-0.0.4.dist-info/WHEEL
trsp-0.0.4.dist-info/entry_points.txt
trsp-0.0.4.dist-info/top_level.txt
trsp-0.0.4.dist-info/RECORD
