Metadata-Version: 2.1
Name: trsp
Version: 0.0.4
Summary: Triton Server Support for building Model repository
Home-page: https://github.com/Ming-doan/trsp
Author: Ming-doan
Author-email: quangminh57dng@gmail.com
License: MIT
Classifier: License :: OSI Approved :: MIT License
Classifier: Programming Language :: Python :: 3.9
Classifier: Operating System :: OS Independent
Requires-Python: >=3.9
License-File: LICENCE
Requires-Dist: pyyaml
Requires-Dist: onnx
